qdax/__init__.py
qdax/custom_types.py
qdax/baselines/__init__.py
qdax/baselines/cmaes.py
qdax/baselines/dads.py
qdax/baselines/dads_smerl.py
qdax/baselines/diayn.py
qdax/baselines/diayn_smerl.py
qdax/baselines/genetic_algorithm.py
qdax/baselines/nsga2.py
qdax/baselines/pbt.py
qdax/baselines/sac.py
qdax/baselines/sac_pbt.py
qdax/baselines/spea2.py
qdax/baselines/td3.py
qdax/baselines/td3_pbt.py
qdax/core/__init__.py
qdax/core/aurora.py
qdax/core/distributed_map_elites.py
qdax/core/map_elites.py
qdax/core/mels.py
qdax/core/mome.py
qdax/core/containers/__init__.py
qdax/core/containers/archive.py
qdax/core/containers/ga_repertoire.py
qdax/core/containers/mapelites_repertoire.py
qdax/core/containers/mels_repertoire.py
qdax/core/containers/mome_repertoire.py
qdax/core/containers/nsga2_repertoire.py
qdax/core/containers/repertoire.py
qdax/core/containers/spea2_repertoire.py
qdax/core/containers/uniform_replacement_archive.py
qdax/core/containers/unstructured_repertoire.py
qdax/core/emitters/__init__.py
qdax/core/emitters/cma_emitter.py
qdax/core/emitters/cma_improvement_emitter.py
qdax/core/emitters/cma_mega_emitter.py
qdax/core/emitters/cma_opt_emitter.py
qdax/core/emitters/cma_pool_emitter.py
qdax/core/emitters/cma_rnd_emitter.py
qdax/core/emitters/dcrl_emitter.py
qdax/core/emitters/dcrl_me_emitter.py
qdax/core/emitters/dpg_emitter.py
qdax/core/emitters/emitter.py
qdax/core/emitters/mees_emitter.py
qdax/core/emitters/multi_emitter.py
qdax/core/emitters/mutation_operators.py
qdax/core/emitters/omg_mega_emitter.py
qdax/core/emitters/pbt_me_emitter.py
qdax/core/emitters/pbt_variation_operators.py
qdax/core/emitters/pga_me_emitter.py
qdax/core/emitters/qdpg_emitter.py
qdax/core/emitters/qpg_emitter.py
qdax/core/emitters/standard_emitters.py
qdax/core/emitters/repertoire_selectors/__init__.py
qdax/core/emitters/repertoire_selectors/mome_uniform_selector.py
qdax/core/emitters/repertoire_selectors/selector.py
qdax/core/emitters/repertoire_selectors/uniform_selector.py
qdax-0.5.0.dist-info/licenses/LICENSE
qdax-0.5.0.dist-info/METADATA
qdax-0.5.0.dist-info/WHEEL
qdax-0.5.0.dist-info/top_level.txt
qdax-0.5.0.dist-info/RECORD
