Metadata-Version: 2.4
Name: qdax
Version: 0.5.0
Summary: A Python Library for Quality-Diversity and NeuroEvolution
Author-email: AIRL and InstaDeep Ltd <adaptive.intelligent.robotics@gmail.com>
License: MIT
Project-URL: Homepage, https://github.com/adaptive-intelligent-robotics/QDax
Project-URL: Bug Tracker, https://github.com/adaptive-intelligent-robotics/QDax/issues
Keywords: Quality-Diversity,NeuroEvolution,Reinforcement Learning,JAX
Classifier: Development Status :: 4 - Beta
Classifier: Environment :: Console
Classifier: Intended Audience :: Science/Research
Classifier: License :: OSI Approved :: MIT License
Classifier: Operating System :: POSIX :: Linux
Classifier: Programming Language :: Python :: 3
Classifier: Programming Language :: Python :: 3.10
Classifier: Programming Language :: Python :: 3.11
Classifier: Programming Language :: Python :: 3.12
Classifier: Topic :: Scientific/Engineering :: Artificial Intelligence
Requires-Python: >=3.10
License-File: LICENSE
Requires-Dist: absl-py>=1.0.0
Requires-Dist: brax>=0.10.4
Requires-Dist: chex>=0.1.86
Requires-Dist: flax>=0.8.5
Requires-Dist: jax>=0.4.28
Requires-Dist: jaxlib>=0.4.28
Requires-Dist: jinja2>=3.1.4
Requires-Dist: jumanji>=0.3.1
Requires-Dist: numpy>=1.26.4
Requires-Dist: optax>=0.1.9
Requires-Dist: scikit-learn>=1.5.1
Requires-Dist: scipy>=1.10.1
Requires-Dist: tensorflow-probability>=0.24.0
Provides-Extra: cuda12
Requires-Dist: jax[cuda12]>=0.4.28; extra == "cuda12"
Dynamic: license-file
